gemini_application/__init__.py
gemini_application/application_abstract.py
gemini_application/chatpopup/__init__.py
gemini_application/chatpopup/chatpopup.py
gemini_application/esp/__init__.py
gemini_application/esp/esp.py
gemini_application/injectionwell/__init__.py
gemini_application/injectionwell/injectionwell_monitoring.py
gemini_application/productionwell/__init__.py
gemini_application/productionwell/annulus_monitoring.py
gemini_application/productionwell/productionwell_performance.py
gemini_application/reportgenerator/__init__.py
gemini_application/reportgenerator/reportgenerator.py
gemini_application/wims/__init__.py
gemini_application/wims/co2_corrosion.py
gemini_application/wims/model_optimization.py
gemini_application/wims/schematics.py
gemini_application-0.3.2.dist-info/LICENSE
gemini_application-0.3.2.dist-info/METADATA
gemini_application-0.3.2.dist-info/WHEEL
gemini_application-0.3.2.dist-info/RECORD
