Metadata-Version: 2.1
Name: gemini-application
Version: 0.3.2
Summary: Core application library of the GEMINI Digital Twin
Home-page: https://nwn.nu/projecten/innovaties/datagedreven-optimalisatie-aardwarmte-systemen/
Author: Ryvo Octaviano
Author-email: ryvo.octaviano@tno.nl
Requires-Python: >=3.11,<4.0
Classifier: Development Status :: 4 - Beta
Classifier: Intended Audience :: Developers
Classifier: Intended Audience :: Science/Research
Classifier: License :: OSI Approved :: GNU General Public License v3 (GPLv3)
Classifier: Operating System :: OS Independent
Classifier: Programming Language :: Python :: 3
Classifier: Programming Language :: Python :: 3.11
Classifier: Programming Language :: Python :: 3.12
Classifier: Topic :: Scientific/Engineering
Classifier: Topic :: Software Development
Requires-Dist: chromadb (>=1.0.12,<2.0.0)
Requires-Dist: flake8 (>=7.0.0,<8.0.0)
Requires-Dist: flake8-docstrings (>=1.7.0,<2.0.0)
Requires-Dist: gemini-framework (==0.3.2)
Requires-Dist: langchain-community (>=0.3.27,<0.4.0)
Requires-Dist: langchain-openai (==0.3.28)
Requires-Dist: lasio (>=0.31,<0.32)
Requires-Dist: ollama (>=0.5.1,<0.6.0)
Requires-Dist: pypdf (>=5.7.0,<6.0.0)
Requires-Dist: pytest (>=8.2.2,<9.0.0)
Requires-Dist: pytest-cov (>=5.0.0,<6.0.0)
Requires-Dist: ruptures (>=1.1.9,<2.0.0)
Project-URL: Documentation, https://readthedocs.org
Project-URL: Repository, https://github.com/GEMINI-Digital-Twin/gemini-model
